{
  "name": "a0b66fa4-775a-428c-992c-a9c6b7a33223",
  "displayName": "VM Forgot password",
  "form": {
  
  },
  "entryFulfillment": {
    "setParameterActions": [ {
      "parameter": "last_page",
      "value": "VM Forgot password"
    }, {
      "parameter": "sms_flow_status",
      "value": "offered"
    }, {
      "parameter": "page_summary",
      "value": "resetting your voicemail password"
    }, {
      "parameter": "page_summaryfr",
      "value": "la réinitialisation du mot de passe de votre boîte vocale"
    }, {
      "parameter": "last_page_summary",
      "value": "Changing or resetting your voicemail password"
    }, {
      "parameter": "last_page_summaryfr",
      "value": "Le changement ou la réinitialisation du mot de passe de votre boite vocale"
    }, {
      "parameter": "mandatory_ss",
      "value": "true"
    } ],
    "conditionalCases": [ {
      "cases": [ {
        "condition": "($session.params.routeDetails.province = \"NB\" OR $session.params.routeDetails.province = \"NS\" OR $session.params.routeDetails.province = \"NF\" OR $session.params.routeDetails.province = \"PE\") AND $session.params.app_first_poc = true",
        "caseContent": [ {
          "message": {
            "text": {
              "text": [ "Pour de l'information sur comment changer ou réinitialiser le mot de passe de votre boite vocale, vous devez utiliser le site Web de TELUS pour obtenir la résolution la plus rapide. Il est simple à utiliser et vous permet d'éviter d'attendre en ligne." ]
            },
            "languageCode": "fr-ca"
          }
        }, {
          "message": {
            "text": {
              "text": [ "Je vous envoie maintenant un lien vers le site Web." ]
            },
            "languageCode": "fr-ca"
          }
        }, {
          "message": {
            "text": {
              "text": [ "Si vous avez encore besoin d'aide, vous pouvez demander un rappel prioritaire à l'assistant virtuel dans votre compte Mon TELUS." ]
            },
            "languageCode": "fr-ca"
          }
        }, {
          "message": {
            "text": {
              "text": [ "To get information on how to change or reset your voicemail password, you must use the TELUS website for the fastest resolution. It's easy to use and allows you to avoid waiting on the line." ]
            },
            "languageCode": "en"
          }
        }, {
          "message": {
            "text": {
              "text": [ "I am sending you a link to the website now." ]
            },
            "languageCode": "en"
          }
        }, {
          "message": {
            "text": {
              "text": [ "If you still need help, you can request a priority call back from the virtual assistant in your My TELUS account." ]
            },
            "languageCode": "en"
          }
        }, {
          "message": {
            "text": {
              "text": [ "To get information on how to change or reset your voicemail password, you must use the TELUS website for the fastest resolution. It's easy to use and allows you to avoid waiting on the line." ]
            },
            "languageCode": "en-ca"
          }
        }, {
          "message": {
            "text": {
              "text": [ "I am sending you a link to the website now." ]
            },
            "languageCode": "en-ca"
          }
        }, {
          "message": {
            "text": {
              "text": [ "If you still need help, you can request a priority call back from the virtual assistant in your My TELUS account." ]
            },
            "languageCode": "en-ca"
          }
        } ]
      }, {
        "caseContent": [ {
          "message": {
            "text": {
              "text": [ "Je peux vous aider à réinitialiser le mot de passe de votre messagerie vocale." ]
            },
            "languageCode": "fr-ca"
          }
        }, {
          "message": {
            "text": {
              "text": [ "I can help with resetting your voicemail password." ]
            },
            "languageCode": "en"
          }
        }, {
          "message": {
            "text": {
              "text": [ "I can help with resetting your voicemail password." ]
            },
            "languageCode": "en-ca"
          }
        }, {
          "message": {
            "text": {
              "text": [ "Would you like to receive a link with instructions on how to reset or change your voicemail password?" ]
            },
            "languageCode": "en-ca"
          }
        } ]
      } ]
    } ]
  },
  "transitionRoutes": [ {
    "condition": "true",
    "triggerFulfillment": {
      "setParameterActions": [ {
        "parameter": "sms_template",
        "value": "0009SaHN7319007E"
      }, {
        "parameter": "sms_template_fr",
        "value": "0009SaHN7319009V"
      }, {
        "parameter": "sms_flow_status",
        "value": "accepted"
      } ]
    },
    "targetFlow": "SMS Flow",
    "name": "41f70d36-c055-4e0d-9197-13101417bbfd"
  } ]
}
