{
  "trainingPhrases": [ {
    "id": "0dee7c1a-a5d3-4ca2-93d4-aa1f5bf5339f",
    "parts": [ {
      "text": "enable my data"
    } ],
    "repeatCount": 1,
    "languageCode": "en-ca"
  }, {
    "id": "0aa31a52-e0c6-4825-9288-a14fdc4e8924",
    "parts": [ {
      "text": "I'd like to enable my data"
    } ],
    "repeatCount": 1,
    "languageCode": "en-ca"
  }, {
    "id": "1d35d6b7-4015-42a2-9fe5-911a0ad16932",
    "parts": [ {
      "text": "enable data on my phone"
    } ],
    "repeatCount": 1,
    "languageCode": "en-ca"
  }, {
    "id": "5035bf94-6f2a-49fc-a583-343d6e478966",
    "parts": [ {
      "text": "Can you tell me where to disable data on my phone"
    } ],
    "repeatCount": 1,
    "languageCode": "en-ca"
  }, {
    "id": "a7c2fa25-f621-4855-85f0-945ec77da806",
    "parts": [ {
      "text": "Can I temporarily disable data on my phone?"
    } ],
    "repeatCount": 1,
    "languageCode": "en-ca"
  }, {
    "id": "057dcc2a-29ad-4eeb-8709-414eb76443bb",
    "parts": [ {
      "text": "how can I enable data?"
    } ],
    "repeatCount": 1,
    "languageCode": "en-ca"
  }, {
    "id": "aea64cdd-5a65-4f68-a679-22b06a518f88",
    "parts": [ {
      "text": "disable my data"
    } ],
    "repeatCount": 1,
    "languageCode": "en-ca"
  }, {
    "id": "1a55aa48-be5a-4d6b-a11e-860d3469b36c",
    "parts": [ {
      "text": "How to enable data on my phone?"
    } ],
    "repeatCount": 1,
    "languageCode": "en-ca"
  }, {
    "id": "1e2c42f5-a6da-4c15-8e4d-df5733801794",
    "parts": [ {
      "text": "need to disable data"
    } ],
    "repeatCount": 1,
    "languageCode": "en-ca"
  }, {
    "id": "2e1d6486-65e3-4665-acbb-8962dd53bb2c",
    "parts": [ {
      "text": "How do i disable data?"
    } ],
    "repeatCount": 1,
    "languageCode": "en-ca"
  }, {
    "id": "acf931bd-9717-49be-8155-62e19960839d",
    "parts": [ {
      "text": "disable data on my phone"
    } ],
    "repeatCount": 1,
    "languageCode": "en-ca"
  }, {
    "id": "f636226d-3be0-4cc3-9d4e-0a317c9a423d",
    "parts": [ {
      "text": "i have a data block on my account"
    } ],
    "repeatCount": 3,
    "languageCode": "en-ca"
  }, {
    "id": "f1803fdc-b72c-474c-8b53-71547aa14915",
    "parts": [ {
      "text": "to remove a data block"
    } ],
    "repeatCount": 3,
    "languageCode": "en-ca"
  }, {
    "id": "6a64d645-25a9-414e-98eb-e9c24a4cf195",
    "parts": [ {
      "text": "they took my data, wonder why they did data block on my phone"
    } ],
    "repeatCount": 3,
    "languageCode": "en-ca"
  }, {
    "id": "107f60a6-478f-4eb1-96d1-1754815e7fe0",
    "parts": [ {
      "text": "remove data blockage"
    } ],
    "repeatCount": 3,
    "languageCode": "en-ca"
  }, {
    "id": "f17c143b-ab86-46de-811b-8fca5a7a1bf9",
    "parts": [ {
      "text": "yes my data was blocked and my billing is supposed to be today and they haven't unblocked it yet is there anyway i can get it unblocked"
    } ],
    "repeatCount": 3,
    "languageCode": "en-ca"
  }, {
    "id": "1666bf54-5290-4520-92c1-daf12de4ce1d",
    "parts": [ {
      "text": "block data"
    } ],
    "repeatCount": 3,
    "languageCode": "en-ca"
  }, {
    "id": "6a44aa87-2417-4fa8-96eb-4e026483e544",
    "parts": [ {
      "text": "i have a data block"
    } ],
    "repeatCount": 3,
    "languageCode": "en-ca"
  }, {
    "id": "43ddeafc-0261-4138-8ff6-6de819a56cad",
    "parts": [ {
      "text": "a data block"
    } ],
    "repeatCount": 3,
    "languageCode": "en-ca"
  }, {
    "id": "be51daa8-7f0d-4ef9-b77f-a62b27ae2211",
    "parts": [ {
      "text": "is my data blocked"
    } ],
    "repeatCount": 3,
    "languageCode": "en-ca"
  }, {
    "id": "86f76925-fefe-4db7-b14d-1cd4929e2dc5",
    "parts": [ {
      "text": "data blocking"
    } ],
    "repeatCount": 3,
    "languageCode": "en-ca"
  }, {
    "id": "4a3d1c1a-99e3-4cb8-b074-dc2ec0459d66",
    "parts": [ {
      "text": "data usage blocked"
    } ],
    "repeatCount": 3,
    "languageCode": "en-ca"
  }, {
    "id": "80e81048-6e32-40b8-bd8c-2091aec1feda",
    "parts": [ {
      "text": "getting my data unblocked"
    } ],
    "repeatCount": 3,
    "languageCode": "en-ca"
  }, {
    "id": "3f4d97a6-dcb0-4410-b0d5-ba4bec7c0dcb",
    "parts": [ {
      "text": "i'm calling about removing a data block on my profile"
    } ],
    "repeatCount": 3,
    "languageCode": "en-ca"
  }, {
    "id": "999bb481-e93e-40b3-a1a9-fe99a5229fab",
    "parts": [ {
      "text": "i need to unblock my data"
    } ],
    "repeatCount": 3,
    "languageCode": "en-ca"
  }, {
    "id": "98757986-56a0-44c6-aa11-1b864d1fff20",
    "parts": [ {
      "text": "i wanna unblock my data usage"
    } ],
    "repeatCount": 3,
    "languageCode": "en-ca"
  }, {
    "id": "84d48191-d837-4082-8edb-f5d00851d12b",
    "parts": [ {
      "text": "yes i'm calling about a data block on my phone profile rather so what is that about"
    } ],
    "repeatCount": 3,
    "languageCode": "en-ca"
  }, {
    "id": "f8f1c801-bbd6-47de-9092-2624606ca754",
    "parts": [ {
      "text": "my data has been blocked because i'm at two fifty i need to reinstate it"
    } ],
    "repeatCount": 3,
    "languageCode": "en-ca"
  }, {
    "id": "797a6599-cd06-4748-aae5-6b56e25a919f",
    "parts": [ {
      "text": "data blocked"
    } ],
    "repeatCount": 3,
    "languageCode": "en-ca"
  }, {
    "id": "7da0fcaa-c90f-428e-9173-f23426234fb9",
    "parts": [ {
      "text": "i'm looking to talk to a a representative to unblock my data"
    } ],
    "repeatCount": 3,
    "languageCode": "en-ca"
  }, {
    "id": "8875aa08-4063-4685-8e70-35cc4514ed16",
    "parts": [ {
      "text": "my data has been blocked i need to turn it back on"
    } ],
    "repeatCount": 3,
    "languageCode": "en-ca"
  }, {
    "id": "c8678da8-3faa-4567-877d-7e05ec50afc3",
    "parts": [ {
      "text": "take off block of data"
    } ],
    "repeatCount": 3,
    "languageCode": "en-ca"
  }, {
    "id": "e6f542f8-c3ad-4df8-86a2-c0d79b3a266e",
    "parts": [ {
      "text": "i'd like to unblock my data"
    } ],
    "repeatCount": 3,
    "languageCode": "en-ca"
  }, {
    "id": "9924d2d3-c4df-4525-b6bc-1ef25fc2a7ee",
    "parts": [ {
      "text": "to unblock internet"
    } ],
    "repeatCount": 3,
    "languageCode": "en-ca"
  }, {
    "id": "7c5062be-01e7-44c5-ac46-9fa5f255abc0",
    "parts": [ {
      "text": "i'd like my data on blocked"
    } ],
    "repeatCount": 3,
    "languageCode": "en-ca"
  }, {
    "id": "ec83f561-346e-42ba-a80c-5fab71da8b1a",
    "parts": [ {
      "text": "i need my data unblocked"
    } ],
    "repeatCount": 3,
    "languageCode": "en-ca"
  }, {
    "id": "7f539de7-747f-41a2-adaa-9280b342c4ea",
    "parts": [ {
      "text": "i need to unlock my data program"
    } ],
    "repeatCount": 3,
    "languageCode": "en-ca"
  }, {
    "id": "f5d69281-4f55-45f7-b319-ccee08fccafa",
    "parts": [ {
      "text": "i would like my data unblocked on my cellphone"
    } ],
    "repeatCount": 3,
    "languageCode": "en-ca"
  }, {
    "id": "98f5f1f9-548d-4257-951e-0ef843bba2ff",
    "parts": [ {
      "text": "unblock my data usage"
    } ],
    "repeatCount": 3,
    "languageCode": "en-ca"
  }, {
    "id": "f8ea6a00-85ec-4a2a-867b-e687a6baecf2",
    "parts": [ {
      "text": "data blockage"
    } ],
    "repeatCount": 3,
    "languageCode": "en-ca"
  }, {
    "id": "8cb3a1d5-6e06-4345-8529-adb006bc1d60",
    "parts": [ {
      "text": "unblock data"
    } ],
    "repeatCount": 3,
    "languageCode": "en-ca"
  }, {
    "id": "2887845d-22e3-4d4f-96ef-7e5423e65987",
    "parts": [ {
      "text": "unlock my data"
    } ],
    "repeatCount": 3,
    "languageCode": "en-ca"
  }, {
    "id": "8c050051-cb1b-4312-9fe0-5ac8dd2541bf",
    "parts": [ {
      "text": "turn data back on"
    } ],
    "repeatCount": 3,
    "languageCode": "en-ca"
  }, {
    "id": "44c97ea1-571f-4da8-9805-b3530169c679",
    "parts": [ {
      "text": "turning data on"
    } ],
    "repeatCount": 3,
    "languageCode": "en-ca"
  }, {
    "id": "07158855-1b50-46d2-851e-ba5707bf739b",
    "parts": [ {
      "text": "turn back on my data"
    } ],
    "repeatCount": 3,
    "languageCode": "en-ca"
  }, {
    "id": "9d523465-e478-49e8-aea3-3938ab9196d0",
    "parts": [ {
      "text": "turn my data back on"
    } ],
    "repeatCount": 3,
    "languageCode": "en-ca"
  }, {
    "id": "56e16d8a-95b8-4b04-b99a-a7fb030ba15d",
    "parts": [ {
      "text": "turn off cellular data on watch"
    } ],
    "repeatCount": 3,
    "languageCode": "en-ca"
  } ]
}
