{
  "name": "af3a2417-5f41-4a9d-8b63-1a40a5a47853",
  "displayName": "epp-plans",
  "transitionRoutes": [ {
    "intent": "head_intent.can_us_plan",
    "triggerFulfillment": {
    
    },
    "targetPage": "CAN US plans",
    "name": "7f47688a-8557-4d2d-ab87-c56c5accfed4"
  }, {
    "intent": "head_intent.plans_available",
    "triggerFulfillment": {
      "setParameterActions": [ {
        "parameter": "route",
        "value": "available_plans"
      } ]
    },
    "targetFlow": "Rate Plans \u0026 Features",
    "name": "a68cc681-8696-4367-b8ce-381127a6323d"
  } ]
}
