{
  "trainingPhrases": [ {
    "parts": [ {
      "text": "Combien y a-t-il de Ko dans 10 Mo?"
    } ],
    "repeatCount": 1,
    "languageCode": "fr-ca"
  }, {
    "parts": [ {
      "text": "1 Mo est-il plus grand qu'un Go ou le contraire?"
    } ],
    "repeatCount": 1,
    "languageCode": "fr-ca"
  }, {
    "parts": [ {
      "text": "Convertir 1 Go en Mo svp!"
    } ],
    "repeatCount": 1,
    "languageCode": "fr-ca"
  }, {
    "parts": [ {
      "text": "J'aimerais savoir si 1 Mo est l'équivalent de 1000 Ko?"
    } ],
    "repeatCount": 1,
    "languageCode": "fr-ca"
  }, {
    "parts": [ {
      "text": "1 Mo est égal à quoi? 1 million d'octets?"
    } ],
    "repeatCount": 1,
    "languageCode": "fr-ca"
  }, {
    "parts": [ {
      "text": "Avez-vous un truc pour savoir combien de Ko, de Mo ou de Go?"
    } ],
    "repeatCount": 1,
    "languageCode": "fr-ca"
  }, {
    "parts": [ {
      "text": "1 Go, ça fait combien de Mo?"
    } ],
    "repeatCount": 1,
    "languageCode": "fr-ca"
  }, {
    "parts": [ {
      "text": "Combien de Ko dans un Go?"
    } ],
    "repeatCount": 1,
    "languageCode": "fr-ca"
  }, {
    "parts": [ {
      "text": "1 Mo en Go?"
    } ],
    "repeatCount": 1,
    "languageCode": "fr-ca"
  }, {
    "parts": [ {
      "text": "Je ne sais pas ce qu'est un mégaoctet."
    } ],
    "repeatCount": 1,
    "languageCode": "fr-ca"
  }, {
    "parts": [ {
      "text": "Je cherche juste à savoir ce que représente un mégaoctet."
    } ],
    "repeatCount": 1,
    "languageCode": "fr-ca"
  }, {
    "parts": [ {
      "text": "Convertissez 1 kilo-octet en gigaoctet"
    } ],
    "repeatCount": 1,
    "languageCode": "fr-ca"
  }, {
    "parts": [ {
      "text": "Convertissez 1 mégaoctet en kilo-octet s'il vous plaît"
    } ],
    "repeatCount": 1,
    "languageCode": "fr-ca"
  }, {
    "parts": [ {
      "text": "Un gigaoctet équivaut à environ un milliard d'octets?"
    } ],
    "repeatCount": 1,
    "languageCode": "fr-ca"
  }, {
    "parts": [ {
      "text": "Cela signifie-t-il donc que 1 mégaoctet de données?"
    } ],
    "repeatCount": 1,
    "languageCode": "fr-ca"
  }, {
    "parts": [ {
      "text": "Je ne comprends pas quand vous dites 1 gigaoctet"
    } ],
    "repeatCount": 1,
    "languageCode": "fr-ca"
  }, {
    "parts": [ {
      "text": "Comment convertir des quantités de données"
    } ],
    "repeatCount": 1,
    "languageCode": "fr-ca"
  }, {
    "parts": [ {
      "text": "J'essaie de comprendre comment les données sont converties, mais je n'en ai aucune idée."
    } ],
    "repeatCount": 1,
    "languageCode": "fr-ca"
  }, {
    "parts": [ {
      "text": "Pouvez-vous expliquer comment les données sont converties?"
    } ],
    "repeatCount": 1,
    "languageCode": "fr-ca"
  }, {
    "parts": [ {
      "text": "Savez-vous comment les données sont converties?"
    } ],
    "repeatCount": 1,
    "languageCode": "fr-ca"
  }, {
    "parts": [ {
      "text": "Mon petit ami a besoin de savoir comment les données sont converties car il utilise beaucoup de données."
    } ],
    "repeatCount": 1,
    "languageCode": "fr-ca"
  }, {
    "parts": [ {
      "text": "Pourriez-vous expliquer comment les données sont converties?"
    } ],
    "repeatCount": 1,
    "languageCode": "fr-ca"
  }, {
    "parts": [ {
      "text": "Existe-t-il un moyen de voir comment les données sont converties en ligne?"
    } ],
    "repeatCount": 1,
    "languageCode": "fr-ca"
  }, {
    "parts": [ {
      "text": "Je ne sais pas comment convertir les données."
    } ],
    "repeatCount": 1,
    "languageCode": "fr-ca"
  }, {
    "parts": [ {
      "text": "Comment convertir des données en mégaoctets?"
    } ],
    "repeatCount": 1,
    "languageCode": "fr-ca"
  }, {
    "parts": [ {
      "text": "Besoin de savoir comment vous convertissez les données."
    } ],
    "repeatCount": 1,
    "languageCode": "fr-ca"
  }, {
    "parts": [ {
      "text": "Comment convertir les données?"
    } ],
    "repeatCount": 1,
    "languageCode": "fr-ca"
  }, {
    "parts": [ {
      "text": "Je ne sais pas comment fonctionne la conversion de données, j'ai besoin de votre aide."
    } ],
    "repeatCount": 1,
    "languageCode": "fr-ca"
  }, {
    "parts": [ {
      "text": "Je ne suis pas sûr de comprendre comment les données sont converties, aidez-moi s'il vous plaît!"
    } ],
    "repeatCount": 1,
    "languageCode": "fr-ca"
  }, {
    "parts": [ {
      "text": "Je me demande comment fonctionne la conversion de données, pourriez-vous m'expliquer?"
    } ],
    "repeatCount": 1,
    "languageCode": "fr-ca"
  }, {
    "parts": [ {
      "text": "Qu'est-ce que le mégaoctet?"
    } ],
    "repeatCount": 1,
    "languageCode": "fr-ca"
  }, {
    "parts": [ {
      "text": "Qu'est-ce que le kilo-octet?"
    } ],
    "repeatCount": 1,
    "languageCode": "fr-ca"
  }, {
    "parts": [ {
      "text": "Qu'est-ce qu'un méga octet?"
    } ],
    "repeatCount": 1,
    "languageCode": "fr-ca"
  }, {
    "parts": [ {
      "text": "Qu'est-ce qu'un kilo-octet?"
    } ],
    "repeatCount": 1,
    "languageCode": "fr-ca"
  }, {
    "parts": [ {
      "text": "Comment les données sont-elles mesurées?"
    } ],
    "repeatCount": 1,
    "languageCode": "fr-ca"
  }, {
    "parts": [ {
      "text": "Comment Telus mesure-t-elle les données?"
    } ],
    "repeatCount": 1,
    "languageCode": "fr-ca"
  }, {
    "parts": [ {
      "text": "Qu'est-ce qu'un giga?"
    } ],
    "repeatCount": 1,
    "languageCode": "fr-ca"
  }, {
    "parts": [ {
      "text": "Combien coûte un gigaoctet?"
    } ],
    "repeatCount": 1,
    "languageCode": "fr-ca"
  }, {
    "parts": [ {
      "text": "Comment les données sont-elles converties?"
    } ],
    "repeatCount": 1,
    "languageCode": "fr-ca"
  }, {
    "parts": [ {
      "text": "Quelle est la différence entre mégaoctet et gigaoctet?"
    } ],
    "repeatCount": 1,
    "languageCode": "fr-ca"
  }, {
    "parts": [ {
      "text": "Combien y a-t-il de mégaoctets dans un gigaoctet?"
    } ],
    "repeatCount": 1,
    "languageCode": "fr-ca"
  }, {
    "parts": [ {
      "text": "Je me pose des questions à propos de la conversion des données."
    } ],
    "repeatCount": 1,
    "languageCode": "fr-ca"
  }, {
    "parts": [ {
      "text": "comment convertir des mégaoctets en gigaoctets?"
    } ],
    "repeatCount": 1,
    "languageCode": "fr-ca"
  }, {
    "parts": [ {
      "text": "combien y a-t-il de mégaoctets dans un kilo-octet"
    } ],
    "repeatCount": 1,
    "languageCode": "fr-ca"
  }, {
    "parts": [ {
      "text": "pouvez-vous m'aider à convertir certaines de mes données"
    } ],
    "repeatCount": 1,
    "languageCode": "fr-ca"
  }, {
    "parts": [ {
      "text": "pouvez-vous m'aider avec une conversion de données"
    } ],
    "repeatCount": 1,
    "languageCode": "fr-ca"
  }, {
    "parts": [ {
      "text": "où puis-je trouver un tableau de conversion de données?"
    } ],
    "repeatCount": 1,
    "languageCode": "fr-ca"
  }, {
    "parts": [ {
      "text": "comment convertir les quantités de données"
    } ],
    "repeatCount": 1,
    "languageCode": "fr-ca"
  }, {
    "parts": [ {
      "text": "merci de convertir mes données en gigaoctets"
    } ],
    "repeatCount": 1,
    "languageCode": "fr-ca"
  }, {
    "parts": [ {
      "text": "J'ai une question concernant la conversion des données"
    } ],
    "repeatCount": 1,
    "languageCode": "fr-ca"
  }, {
    "parts": [ {
      "text": "Je suis curieux par rapport à la conversion des données"
    } ],
    "repeatCount": 1,
    "languageCode": "fr-ca"
  }, {
    "parts": [ {
      "text": "comment ça marche pour la conversion de données"
    } ],
    "repeatCount": 1,
    "languageCode": "fr-ca"
  }, {
    "parts": [ {
      "text": "C'est quoi qui est considéré comme des données?"
    } ],
    "repeatCount": 1,
    "languageCode": "fr-ca"
  }, {
    "parts": [ {
      "text": "combien de kilo-octets dans un gigaoctet?"
    } ],
    "repeatCount": 1,
    "languageCode": "fr-ca"
  }, {
    "parts": [ {
      "text": "nous cherchons un moyen de convertir nos données"
    } ],
    "repeatCount": 1,
    "languageCode": "fr-ca"
  }, {
    "parts": [ {
      "text": "comment faire une conversion de données"
    } ],
    "repeatCount": 1,
    "languageCode": "fr-ca"
  }, {
    "parts": [ {
      "text": "pouvez-vous m'aider à convertir des mégaoctets en kilo-octets?"
    } ],
    "repeatCount": 1,
    "languageCode": "fr-ca"
  }, {
    "parts": [ {
      "text": "comment convertir mes données"
    } ],
    "repeatCount": 1,
    "languageCode": "fr-ca"
  }, {
    "parts": [ {
      "text": "conversion de données"
    } ],
    "repeatCount": 1,
    "languageCode": "fr-ca"
  }, {
    "parts": [ {
      "text": "j'ai besoin de convertir mon volume d'utilisation de données, pouvez-vous m'aider?"
    } ],
    "repeatCount": 1,
    "languageCode": "fr-ca"
  } ]
}
